mlwitheasy/Classification.py
mlwitheasy/Regression.py
mlwitheasy/__init__.py
mlwitheasy/custom_exception.py
mlwitheasy/logger.py
mlwitheasy-0.0.3.dist-info/LICENSE
mlwitheasy-0.0.3.dist-info/METADATA
mlwitheasy-0.0.3.dist-info/WHEEL
mlwitheasy-0.0.3.dist-info/top_level.txt
mlwitheasy-0.0.3.dist-info/RECORD
